Awesome_Linear_Regression/__init__.py
Awesome_Linear_Regression/linearregression.py
Awesome_Linear_Regression-1.0.0.dist-info/LICENSE
Awesome_Linear_Regression-1.0.0.dist-info/METADATA
Awesome_Linear_Regression-1.0.0.dist-info/WHEEL
Awesome_Linear_Regression-1.0.0.dist-info/top_level.txt
Awesome_Linear_Regression-1.0.0.dist-info/RECORD
