Metadata-Version: 2.1
Name: Awesome-Linear-Regression
Version: 1.0.0
Summary: Awesome Linear Regression , is a mathematics API written in Python.
Author-email: Ouedraogo Somkieta Rahim Alex <s.r.a.ouedraogo@gmail.com>
Project-URL: Homepage, https://github.com/somkietacode/Awesome_Linear_Regression
Project-URL: Bug Tracker, https://github.com/somkietacode/Awesome_Linear_Regression/issues
Classifier: Programming Language :: Python :: 3
Classifier: License :: OSI Approved :: MIT License
Classifier: Operating System :: OS Independent
Requires-Python: >=3.7
License-File: LICENSE
Requires-Dist: numpy
Requires-Dist: importlib-metadata ; python_version < "3.7"
